PyEMD/BEMD.py
PyEMD/CEEMDAN.py
PyEMD/EEMD.py
PyEMD/EMD.py
PyEMD/EMD2d.py
PyEMD/EMD_matlab.py
PyEMD/__init__.py
PyEMD/checks.py
PyEMD/compact.py
PyEMD/splines.py
PyEMD/types.py
PyEMD/utils.py
PyEMD/visualisation.py
PyEMD/experimental/__init__.py
PyEMD/experimental/jitemd.py
PyEMD/tests/__init__.py
PyEMD/tests/test_all.py
PyEMD/tests/test_bemd.py
PyEMD/tests/test_ceemdan.py
PyEMD/tests/test_checks.py
PyEMD/tests/test_compact.py
PyEMD/tests/test_eemd.py
PyEMD/tests/test_emd.py
PyEMD/tests/test_emd2d.py
PyEMD/tests/test_emd_matlab.py
PyEMD/tests/test_extrema.py
PyEMD/tests/test_splines.py
PyEMD/tests/test_utils.py
PyEMD/tests/test_visualization.py
emd_signal-1.8.0.dist-info/licenses/LICENSE.md
emd_signal-1.8.0.dist-info/METADATA
emd_signal-1.8.0.dist-info/WHEEL
emd_signal-1.8.0.dist-info/top_level.txt
emd_signal-1.8.0.dist-info/RECORD
