Metadata-Version: 2.4
Name: EMD-signal
Version: 1.8.0
Summary: Implementation of the Empirical Mode Decomposition (EMD) and its variations
Home-page: https://github.com/laszukdawid/PyEMD
Author: Dawid Laszuk
Author-email: pyemd@dawid.lasz.uk
License: Apache-2.0
Keywords: signal decomposition data analysis
Classifier: Intended Audience :: Information Technology
Classifier: Intended Audience :: Science/Research
Classifier: Topic :: Scientific/Engineering
Classifier: Topic :: Scientific/Engineering :: Information Analysis
Classifier: Topic :: Scientific/Engineering :: Mathematics
Requires-Python: <4,>=3.6
License-File: LICENSE.md
Requires-Dist: numpy>=1.12
Requires-Dist: scipy>=0.19
Requires-Dist: pathos>=0.2.1
Requires-Dist: tqdm<5.0,>=4.64.0
Provides-Extra: doc
Requires-Dist: sphinx; extra == "doc"
Requires-Dist: sphinx_rtd_theme; extra == "doc"
Requires-Dist: numpydoc; extra == "doc"
Provides-Extra: jit
Requires-Dist: numba==0.56.*; extra == "jit"
Provides-Extra: dev
Requires-Dist: pycodestyle==2.11.*; extra == "dev"
Requires-Dist: black==24.3.*; extra == "dev"
Requires-Dist: isort==5.12.*; extra == "dev"
Provides-Extra: test
Requires-Dist: pytest; extra == "test"
Requires-Dist: codecov; extra == "test"
Dynamic: license-file
